cdd/__init__.cp313-win_amd64.pyd
cdd/__init__.pyi
cdd/gmp.cp313-win_amd64.pyd
cdd/gmp.pyi
cdd/py.typed
pycddlib-3.0.2.dist-info/AUTHORS
pycddlib-3.0.2.dist-info/LICENSE.md
pycddlib-3.0.2.dist-info/METADATA
pycddlib-3.0.2.dist-info/WHEEL
pycddlib-3.0.2.dist-info/top_level.txt
pycddlib-3.0.2.dist-info/RECORD
