Metadata-Version: 2.2
Name: pycddlib
Version: 3.0.2
Summary: A Python wrapper for cddlib
Author-email: "Matthias C. M. Troffaes" <matthias.troffaes@gmail.com>
Project-URL: Homepage, https://github.com/mcmtroffaes/pycddlib
Project-URL: Documentation, https://pycddlib.readthedocs.io/
Project-URL: Repository, https://github.com/mcmtroffaes/pycddlib.git
Project-URL: Issues, https://github.com/mcmtroffaes/pycddlib/issues
Project-URL: Changelog, https://github.com/mcmtroffaes/pycddlib/blob/develop/CHANGELOG.rst
Keywords: convex, polyhedron, linear programming, double description method
Classifier: Development Status :: 4 - Beta
Classifier: License :: OSI Approved :: GNU General Public License v2 or later (GPLv2+)
Classifier: Intended Audience :: Science/Research
Classifier: Topic :: Scientific/Engineering :: Mathematics
Classifier: Programming Language :: C
Classifier: Programming Language :: Cython
Classifier: Programming Language :: Python
Classifier: Programming Language :: Python :: 3
Classifier: Operating System :: OS Independent
Requires-Python: >=3.9
License-File: LICENSE.md
License-File: AUTHORS
Provides-Extra: test
Requires-Dist: pytest; extra == "test"
Requires-Dist: numpy; extra == "test"
Requires-Dist: gmpy2; extra == "test"
Requires-Dist: mypy; extra == "test"
Requires-Dist: black; extra == "test"
Requires-Dist: isort; extra == "test"
Requires-Dist: flake8; extra == "test"
Provides-Extra: doc
Requires-Dist: sphinx; extra == "doc"
